aio_websocket_pool/__init__.py
aio_websocket_pool/_conn.py
aio_websocket_pool/_pool.py
aio_websocket_pool-0.1.0.dist-info/LICENSE
aio_websocket_pool-0.1.0.dist-info/METADATA
aio_websocket_pool-0.1.0.dist-info/WHEEL
aio_websocket_pool-0.1.0.dist-info/RECORD
