Metadata-Version: 2.3
Name: aio-websocket-pool
Version: 0.1.0
Summary: Asynchronous WebSocket connection pool for Python with connection reuse, health monitoring, and automatic cleanup
License: MIT
Keywords: websocket,connection-pool,async,asyncio,websockets,pool
Author: BoChen SHEN
Author-email: 6goddddddd@gmail.com
Requires-Python: >=3.11,<3.13
Classifier: Development Status :: 4 - Beta
Classifier: Framework :: AsyncIO
Classifier: Intended Audience :: Developers
Classifier: License :: OSI Approved :: MIT License
Classifier: Operating System :: OS Independent
Classifier: Programming Language :: Python :: 3
Classifier: Programming Language :: Python :: 3.11
Classifier: Programming Language :: Python :: 3.12
Classifier: Topic :: Internet :: WWW/HTTP
Classifier: Topic :: Software Development :: Libraries
Classifier: Topic :: Software Development :: Libraries :: Python Modules
Classifier: Typing :: Typed
Requires-Dist: tenacity (>=9.1.2,<10.0.0)
Requires-Dist: websockets (>=15.0.1,<16.0.0)
Project-URL: Documentation, https://github.com/your-username/aio-websocket-pool
Project-URL: Homepage, https://github.com/your-username/aio-websocket-pool
Project-URL: Repository, https://github.com/your-username/aio-websocket-pool
